IrcBot/__init__.py
IrcBot/bot.py
IrcBot/dcc.py
IrcBot/message.py
IrcBot/shortestPrefix.py
IrcBot/sqlitedb.py
IrcBot/utils.py
re_ircbot-1.7.0.dist-info/LICENSE
re_ircbot-1.7.0.dist-info/METADATA
re_ircbot-1.7.0.dist-info/WHEEL
re_ircbot-1.7.0.dist-info/top_level.txt
re_ircbot-1.7.0.dist-info/RECORD
