Metadata-Version: 2.1
Name: re-ircbot
Version: 1.7.0
Summary: A simple async irc bot framework with regex command definitions and data permanency
Home-page: https://github.com/matheusfillipe/ircbot
Author: Matheus Fillipe
Author-email: mattf@tilde.club
License: UNKNOWN
Platform: UNKNOWN
Classifier: Development Status :: 5 - Production/Stable
Classifier: Programming Language :: Python :: 3
Classifier: License :: OSI Approved :: MIT License
Classifier: Operating System :: OS Independent
Classifier: Topic :: Software Development :: Libraries :: Python Modules
Classifier: Topic :: Communications :: Chat
Classifier: Topic :: Internet
Requires-Python: >=3.4
License-File: LICENSE
Requires-Dist: trio ==0.22.0
Requires-Dist: cachetools ==5.3.0
Requires-Dist: trio-asyncio ==0.12.0
